README.md
setup.py
src/tfsm/__init__.py
src/tfsm/exceptions.py
src/tfsm/fsm.py
src/tfsm/models.py
src/tfsm/settings.py
src/tfsm/utils.py
src/tfsm.egg-info/PKG-INFO
src/tfsm.egg-info/SOURCES.txt
src/tfsm.egg-info/dependency_links.txt
src/tfsm.egg-info/requires.txt
src/tfsm.egg-info/top_level.txt
src/tfsm/machines/__init__.py
src/tfsm/machines/talg/__init__.py
src/tfsm/machines/talg/conditions.py
src/tfsm/machines/talg/parameters.py
src/tfsm/machines/talg/states.py
src/tfsm/machines/talg/transitions.py
src/tfsm/machines/tsys/__init__.py
src/tfsm/machines/tsys/conditions.py
src/tfsm/machines/tsys/states.py
src/tfsm/machines/tsys/transitions.py
src/tfsm/tests/__init__.py
src/tfsm/tests/__main__.py
src/tfsm/tests/test_models.py
src/tfsm/tests/test_tfsm.py