Metadata-Version: 2.1
Name: tfsm
Version: 1.0.1
Summary: A Trader Finite State Machine
Home-page: https://github.com/edwardyliu/Ars
Author: Edward Y. Liu
Author-email: edwardy.liu@mail.utoronto.ca
License: UNKNOWN
Platform: UNKNOWN
Classifier: Development Status :: 3 - Alpha
Classifier: Programming Language :: Python :: 3.6
Classifier: Operating System :: OS Independent
Requires-Python: >=3.6.8
